ReunionLog/__init__.py
ReunionLog/OAuth/Authentication.py
ReunionLog/OAuth/EndConnection.py
ReunionLog/OAuth/__init__.py
ReunionLog/Report/ReportAbilities.py
ReunionLog/Report/ReportEndTime.py
ReunionLog/Report/ReportEventsDamageDone.py
ReunionLog/Report/ReportEventsDeath.py
ReunionLog/Report/ReportEventsInterrupts.py
ReunionLog/Report/ReportNames.py
ReunionLog/Report/ReportStartTime.py
ReunionLog/Report/__init__.py
ReunionLog-0.3.1.2.dist-info/LICENCE
ReunionLog-0.3.1.2.dist-info/METADATA
ReunionLog-0.3.1.2.dist-info/WHEEL
ReunionLog-0.3.1.2.dist-info/top_level.txt
ReunionLog-0.3.1.2.dist-info/RECORD
