Metadata-Version: 2.1
Name: ReunionLog
Version: 0.3.1.2
Summary: A small package to access and use WarcraftLogs API
Home-page: https://github.com/nickgismokato/ReunionLog
Author: nickgismokato
Author-email: nickvillumlaursen@gmail.com
License: MIT License
Keywords: python,WarcraftLogs-API,package
Classifier: Development Status :: 2 - Pre-Alpha
Classifier: Intended Audience :: End Users/Desktop
Classifier: Intended Audience :: Other Audience
Classifier: Programming Language :: Python :: 3
Classifier: Operating System :: OS Independent
Requires-Python: >=3.10
License-File: LICENCE
